octonomicon_shared/__init__.py
octonomicon_shared/errors/EnvError.py
octonomicon_shared/errors/__init__.py
octonomicon_shared/utils/__init__.py
octonomicon_shared/utils/env/load_env_variable.py
octonomicon_shared-0.1.4.dist-info/METADATA
octonomicon_shared-0.1.4.dist-info/WHEEL
octonomicon_shared-0.1.4.dist-info/top_level.txt
octonomicon_shared-0.1.4.dist-info/RECORD
