Metadata-Version: 2.4
Name: octonomicon-shared
Version: 0.1.4
Summary: Shared utilities for Octonomicon projects
License: MIT
Requires-Python: >=3.8
